maihem/__init__.py
maihem/api.py
maihem/cli.py
maihem/clients.py
maihem/decorator.py
maihem/errors.py
maihem/evaluators.py
maihem/logger.py
maihem/otel_client.py
maihem/api_client/maihem_client/__init__.py
maihem/api_client/maihem_client/client.py
maihem/api_client/maihem_client/errors.py
maihem/api_client/maihem_client/py.typed
maihem/api_client/maihem_client/types.py
maihem/api_client/maihem_client/api/__init__.py
maihem/api_client/maihem_client/api/admin_internal/__init__.py
maihem/api_client/maihem_client/api/admin_internal/admin_internal_admin_create_evaluation_review.py
maihem/api_client/maihem_client/api/admin_internal/admin_internal_admin_edit_evaluation.py
maihem/api_client/maihem_client/api/admin_internal/admin_internal_admin_get_evaluation_review_audits.py
maihem/api_client/maihem_client/api/admin_internal/admin_internal_admin_get_evaluation_review_states.py
maihem/api_client/maihem_client/api/agents/__init__.py
maihem/api_client/maihem_client/api/agents/agents_create_agent_target.py
maihem/api_client/maihem_client/api/agents/agents_create_agent_target_revision.py
maihem/api_client/maihem_client/api/agents/agents_get_agent_target.py
maihem/api_client/maihem_client/api/agents/agents_get_agent_target_revisions.py
maihem/api_client/maihem_client/api/agents/agents_get_agent_targets.py
maihem/api_client/maihem_client/api/agents/agents_get_target_agent_workflow.py
maihem/api_client/maihem_client/api/agents/agents_get_target_agent_workflows.py
maihem/api_client/maihem_client/api/agents/agents_set_active_agent_target.py
maihem/api_client/maihem_client/api/conversations/__init__.py
maihem/api_client/maihem_client/api/conversations/conversations_get_conversation.py
maihem/api_client/maihem_client/api/datasets/__init__.py
maihem/api_client/maihem_client/api/datasets/datasets_create_dataset.py
maihem/api_client/maihem_client/api/datasets/datasets_create_dataset_item.py
maihem/api_client/maihem_client/api/datasets/datasets_get_datasets.py
maihem-1.7.7.dist-info/licenses/LICENSE
maihem-1.7.7.dist-info/METADATA
maihem-1.7.7.dist-info/WHEEL
maihem-1.7.7.dist-info/entry_points.txt
maihem-1.7.7.dist-info/top_level.txt
maihem-1.7.7.dist-info/RECORD
