Metadata-Version: 2.4
Name: maihem
Version: 1.7.7
Summary: LLM evaluations and synthetic data generation with the MAIHEM models
Author: MAIHEM
License: MIT License
Project-URL: Homepage, https://github.com/maihemlabs/maihem
Keywords: genAI,LLM,evaluation,data,generation,synthetic
Classifier: License :: OSI Approved :: MIT License
Classifier: Programming Language :: Python
Classifier: Programming Language :: Python :: 3
Requires-Python: >=3.10
License-File: LICENSE
Requires-Dist: requests
Requires-Dist: pandas
Requires-Dist: pydantic
Requires-Dist: pycountry
Requires-Dist: pydantic_extra_types
Requires-Dist: httpx
Requires-Dist: attrs
Requires-Dist: loguru
Requires-Dist: tqdm
Requires-Dist: anyio
Requires-Dist: docx2txt
Requires-Dist: yaspin
Requires-Dist: pyyaml
Requires-Dist: pillow
Requires-Dist: click
Requires-Dist: PyPDF2
Requires-Dist: opentelemetry-sdk>=1.31.1
Requires-Dist: opentelemetry-api>=1.31.1
Requires-Dist: opentelemetry-exporter-otlp>=1.31.1
Requires-Dist: pymupdf>=1.25.5
Requires-Dist: orjson>=3.10.16
Dynamic: license-file
